calculator/__init__.py
calculator/calculator.py
nn_calculator-0.4.dist-info/DESCRIPTION.rst
nn_calculator-0.4.dist-info/METADATA
nn_calculator-0.4.dist-info/RECORD
nn_calculator-0.4.dist-info/WHEEL
nn_calculator-0.4.dist-info/metadata.json
nn_calculator-0.4.dist-info/top_level.txt
