Metadata-Version: 2.0
Name: nn-calculator
Version: 0.4
Summary: Simple application to teach CI/CD
Home-page: https://gitlab.com/MvdLinden/nn-cicd
Author: Marco van der Linden
Author-email: mvanderlinden@xebia.com
License: UNKNOWN
Keywords: cicd,example
Platform: UNKNOWN
